xnbs/__init__.py
xnbs/_modidx.py
xnbs/load.py
xnbs-0.0.2.dist-info/LICENSE
xnbs-0.0.2.dist-info/METADATA
xnbs-0.0.2.dist-info/WHEEL
xnbs-0.0.2.dist-info/entry_points.txt
xnbs-0.0.2.dist-info/top_level.txt
xnbs-0.0.2.dist-info/RECORD
