Metadata-Version: 2.1
Name: xnbs
Version: 0.0.2
Summary: xnbs
Home-page: https://github.com/dsm-72/xnbs
Author: dsm-72
Author-email: sumner.magruder@yale.edu
License: Apache Software License 2.0
Keywords: xnbs extra extras notebooks nb nbs nbdev utils utilities jupyter
Classifier: Development Status :: 4 - Beta
Classifier: Intended Audience :: Developers
Classifier: Natural Language :: English
Classifier: Programming Language :: Python :: 3.11
Classifier: License :: OSI Approved :: Apache Software License
Requires-Python: >=3.11
License-File: LICENSE
Requires-Dist: nchr
Requires-Dist: nlit
Requires-Dist: chck
Provides-Extra: dev
